survol
tests
